anycast_healthchecker/__init__.py
anycast_healthchecker/healthchecker.py
anycast_healthchecker/main.py
anycast_healthchecker/servicecheck.py
anycast_healthchecker/utils.py
anycast_healthchecker-0.9.10.dist-info/AUTHORS
anycast_healthchecker-0.9.10.dist-info/LICENSE.md
anycast_healthchecker-0.9.10.dist-info/METADATA
anycast_healthchecker-0.9.10.dist-info/WHEEL
anycast_healthchecker-0.9.10.dist-info/entry_points.txt
anycast_healthchecker-0.9.10.dist-info/pbr.json
anycast_healthchecker-0.9.10.dist-info/top_level.txt
anycast_healthchecker-0.9.10.dist-info/RECORD
