Metadata-Version: 2.2
Name: anycast-healthchecker
Version: 0.9.10
Summary: A healthchecker for Anycasted Services
Home-page: https://github.com/unixsurfer/anycast_healthchecker
Author: Pavlos Parissis
Author-email: Pavlos Parissis <pavlos.parissis@gmail.com>
Maintainer: Pavlos Parissis
Maintainer-email: pavlos.parissis@gmail.com
License: Apache 2.0
Project-URL: documentation, https://github.com/unixsurfer/anycast_healthchecker#readme
Project-URL: repository, https://github.com/unixsurfer/anycast_healthchecker
Keywords: healthchecker,anycast,ECMP
Classifier: Development Status :: 5 - Production/Stable
Classifier: Environment :: Console
Classifier: Intended Audience :: Information Technology
Classifier: Intended Audience :: System Administrators
Classifier: Natural Language :: English
Classifier: Operating System :: POSIX
Classifier: Programming Language :: Python
Classifier: Topic :: System :: Monitoring
Classifier: Topic :: Utilities
License-File: LICENSE.md
License-File: AUTHORS
Requires-Dist: docopt
Requires-Dist: prometheus-client
Requires-Dist: python-json-logger
Dynamic: author
Dynamic: home-page
Dynamic: maintainer
Dynamic: maintainer-email
